MANIFEST.in
README.txt
setup.cfg
setup.py
collective/__init__.py
collective.miscbehaviors.egg-info/PKG-INFO
collective.miscbehaviors.egg-info/SOURCES.txt
collective.miscbehaviors.egg-info/dependency_links.txt
collective.miscbehaviors.egg-info/entry_points.txt
collective.miscbehaviors.egg-info/namespace_packages.txt
collective.miscbehaviors.egg-info/not-zip-safe
collective.miscbehaviors.egg-info/paster_plugins.txt
collective.miscbehaviors.egg-info/requires.txt
collective.miscbehaviors.egg-info/top_level.txt
collective/miscbehaviors/__init__.py
collective/miscbehaviors/configure.zcml
collective/miscbehaviors/indexer.py
collective/miscbehaviors/tests.py
collective/miscbehaviors/behavior/__init__.py
collective/miscbehaviors/behavior/bodytext.py
collective/miscbehaviors/behavior/configure.zcml
collective/miscbehaviors/behavior/contactinfo.py
collective/miscbehaviors/behavior/fileattachment.py
collective/miscbehaviors/behavior/leadimage.py
collective/miscbehaviors/behavior/paypal.py
collective/miscbehaviors/behavior/remoteurl.py
collective/miscbehaviors/behavior/startenddate.py
collective/miscbehaviors/behavior/utils.py
collective/miscbehaviors/browser/__init__.py
collective/miscbehaviors/browser/configure.zcml
collective/miscbehaviors/browser/leadimage.pt
collective/miscbehaviors/browser/leadimage.py
collective/miscbehaviors/content/__init__.py
collective/miscbehaviors/content/configure.zcml
collective/miscbehaviors/locales/collective.miscbehaviors.pot
collective/miscbehaviors/locales/locales-here.txt
collective/miscbehaviors/locales/update.sh
collective/miscbehaviors/locales/fi/LC_MESSAGES/collective.miscbehaviors.po
collective/miscbehaviors/portlets/__init__.py
collective/miscbehaviors/portlets/configure.zcml
collective/miscbehaviors/portlets/imageportlet.pt
collective/miscbehaviors/portlets/imageportlet.py
collective/miscbehaviors/portlets/paypal.pt
collective/miscbehaviors/portlets/paypal.py
collective/miscbehaviors/profiles/default/metadata.xml
collective/miscbehaviors/profiles/default/portlets.xml
collective/miscbehaviors/profiles/default/types.xml
docs/HISTORY.txt
docs/INSTALL.txt
docs/LICENSE.GPL
docs/LICENSE.txt