Metadata-Version: 1.1
Name: collective.miscbehaviors
Version: 0.2.2
Summary: Miscellaneous behaviors for Plone
Home-page: http://svn.plone.org/svn/collective/collective.miscbehaviors
Author: Izhar Firdaus
Author-email: izhar@inigo-tech.com
License: GPL
Keywords: plone dexterity behavior
Platform: UNKNOWN
Classifier: Framework :: Plone
Classifier: Programming Language :: Python
